quorachallenge/__init__.py
quorachallenge/_core.py
quorachallenge/exemplar.py
quorachallenge/quorachallenge.py
quorachallenge/version.py
quorachallenge-1.0.3.dist-info/LICENSE.rst
quorachallenge-1.0.3.dist-info/METADATA
quorachallenge-1.0.3.dist-info/WHEEL
quorachallenge-1.0.3.dist-info/top_level.txt
quorachallenge-1.0.3.dist-info/RECORD
