Metadata-Version: 2.1
Name: quorachallenge
Version: 1.0.3
Summary: Quora Challenge: The framework for the Quora development challenges - supporting project description and testing.
Home-page: http://quorachallenge.readthedocs.org/en/latest/
Author: Tony Flury
Author-email: anthony.flury@btinternet.com
License: GNU General Public License (GPL)
Keywords: Quora Challenge Framework Test
Platform: UNKNOWN
Classifier: Development Status :: 3 - Alpha
Classifier: Intended Audience :: Developers
Classifier: Topic :: Software Development :: Libraries :: Python Modules
Classifier: License :: OSI Approved :: GNU General Public License (GPL)
Classifier: Programming Language :: Python :: 3.6
Classifier: Programming Language :: Python :: 3.7
Classifier: Programming Language :: Python :: 3.8
Requires-Python: >=3.6
Requires-Dist: click
Requires-Dist: docutils
Requires-Dist: requests
Requires-Dist: sphinx
Requires-Dist: sphinx-rtd-theme
Provides-Extra: dev
Provides-Extra: test
Requires-Dist: coverage ; extra == 'test'
